line_async_webhook/__init__.py
line_async_webhook/py.typed
line_async_webhook-1.0.1.dist-info/LICENSE
line_async_webhook-1.0.1.dist-info/METADATA
line_async_webhook-1.0.1.dist-info/WHEEL
line_async_webhook-1.0.1.dist-info/RECORD
