Metadata-Version: 2.1
Name: line-async-webhook
Version: 1.0.1
Summary: 
Author: Nutchanon Ninyawee
Author-email: nutchanon@codustry.com
Requires-Python: >=3.10,<4.0
Classifier: Programming Language :: Python :: 3
Classifier: Programming Language :: Python :: 3.10
Classifier: Programming Language :: Python :: 3.11
Requires-Dist: asyncer (>=0.0.2,<0.0.3)
Requires-Dist: line-bot-sdk (>=2.4.2,<3.0.0)
